openai_websearch_mcp/__init__.py
openai_websearch_mcp/__main__.py
openai_websearch_mcp/cli.py
openai_websearch_mcp/server.py
openai_websearch_mcp-0.4.3.dist-info/METADATA
openai_websearch_mcp-0.4.3.dist-info/WHEEL
openai_websearch_mcp-0.4.3.dist-info/entry_points.txt
openai_websearch_mcp-0.4.3.dist-info/licenses/LICENSE
openai_websearch_mcp-0.4.3.dist-info/RECORD
